nattouclock/__init__.py
nattouclock/icon.png
nattouclock/outlinedlabel.py
nattouclock/widget.py
nattouclock-0.1.0.dist-info/METADATA
nattouclock-0.1.0.dist-info/WHEEL
nattouclock-0.1.0.dist-info/entry_points.txt
nattouclock-0.1.0.dist-info/RECORD
