Metadata-Version: 2.1
Name: nattouclock
Version: 0.1.0
Summary: Clock widget for Linux
Home-page: https://github.com/nattoujam/nattou-clock
Author: nattoujam
Author-email: Public.kyuuanago@gmail.com
Requires-Python: >=3.12,<4.0
Classifier: Programming Language :: Python :: 3
Classifier: Programming Language :: Python :: 3.12
Requires-Dist: PyQt5 (==5.15.2)
Requires-Dist: pyyaml (>=6.0.1,<7.0.0)
Project-URL: Repository, https://github.com/nattoujam/nattou-clock
